<?xml version="1.0" encoding="UTF-8" ?>
<!DOCTYPE mapper PUBLIC "-//mybatis.org//DTD Mapper 3.0//EN" "http://mybatis.org/dtd/mybatis-3-mapper.dtd" >
<mapper namespace="com.website.service.mapper.ReplyCommentMapper" >
  <resultMap id="BaseResultMap" type="com.website.service.entity.ReplyComment" >
    <!--
      WARNING - @mbggenerated
      This element is automatically generated by MyBatis Generator, do not modify.
      This element was generated on Fri Aug 07 15:50:06 GMT+08:00 2020.
    -->
    <id column="id" property="id" jdbcType="VARCHAR" />
    <result column="comment_id" property="commentId" jdbcType="VARCHAR" />
    <result column="user_img" property="userImg" jdbcType="VARCHAR" />
    <result column="user_name" property="userName" jdbcType="VARCHAR" />
    <result column="reply_content" property="replyContent" jdbcType="VARCHAR" />
  </resultMap>
  <delete id="deleteByPrimaryKey" parameterType="java.lang.String" >
    <!--
      WARNING - @mbggenerated
      This element is automatically generated by MyBatis Generator, do not modify.
      This element was generated on Fri Aug 07 15:50:06 GMT+08:00 2020.
    -->
    delete from reply_comment
    where id = #{id,jdbcType=VARCHAR}
  </delete>
  <insert id="insert" parameterType="com.website.service.entity.ReplyComment" >
    <!--
      WARNING - @mbggenerated
      This element is automatically generated by MyBatis Generator, do not modify.
      This element was generated on Fri Aug 07 15:50:06 GMT+08:00 2020.
    -->
    insert into reply_comment (id, comment_id, user_img, 
      user_name, reply_content)
    values (#{id,jdbcType=VARCHAR}, #{commentId,jdbcType=VARCHAR}, #{userImg,jdbcType=VARCHAR}, 
      #{userName,jdbcType=VARCHAR}, #{replyContent,jdbcType=VARCHAR})
  </insert>
  <update id="updateByPrimaryKey" parameterType="com.website.service.entity.ReplyComment" >
    <!--
      WARNING - @mbggenerated
      This element is automatically generated by MyBatis Generator, do not modify.
      This element was generated on Fri Aug 07 15:50:06 GMT+08:00 2020.
    -->
    update reply_comment
    set comment_id = #{commentId,jdbcType=VARCHAR},
      user_img = #{userImg,jdbcType=VARCHAR},
      user_name = #{userName,jdbcType=VARCHAR},
      reply_content = #{replyContent,jdbcType=VARCHAR}
    where id = #{id,jdbcType=VARCHAR}
  </update>
  <select id="selectByPrimaryKey" resultMap="BaseResultMap" parameterType="java.lang.String" >
    <!--
      WARNING - @mbggenerated
      This element is automatically generated by MyBatis Generator, do not modify.
      This element was generated on Fri Aug 07 15:50:06 GMT+08:00 2020.
    -->
    select id, comment_id, user_img, user_name, reply_content
    from reply_comment
    where id = #{id,jdbcType=VARCHAR}
  </select>
  <select id="selectAll" resultMap="BaseResultMap" >
    <!--
      WARNING - @mbggenerated
      This element is automatically generated by MyBatis Generator, do not modify.
      This element was generated on Fri Aug 07 15:50:06 GMT+08:00 2020.
    -->
    select id, comment_id, user_img, user_name, reply_content
    from reply_comment
  </select>
</mapper>